pygments_graphql.py
pygments_graphql-1.0.0.dist-info/METADATA
pygments_graphql-1.0.0.dist-info/WHEEL
pygments_graphql-1.0.0.dist-info/entry_points.txt
pygments_graphql-1.0.0.dist-info/top_level.txt
pygments_graphql-1.0.0.dist-info/RECORD
